llpm/__init__.py
llpm/shell.py
llpm/style.py
llpm/utils.py
llpm-0.5.0.dist-info/entry_points.txt
llpm-0.5.0.dist-info/METADATA
llpm-0.5.0.dist-info/WHEEL
llpm-0.5.0.dist-info/RECORD
